labdevices/__init__.py
labdevices/exceptions.py
labdevices/functiongenerator.py
labdevices/gcodedevice.py
labdevices/gpio.py
labdevices/i2cbus.py
labdevices/oscilloscope.py
labdevices/powersupply.py
labdevices/pressuregauge.py
labdevices/scpi.py
labdevices/serialringbuffer.py
labdevices/siunits.py
labdevices/spectrumanalyzer.py
labdevices/spibus.py
pylabdevs_tspspi-0.0.18.dist-info/LICENSE.md
pylabdevs_tspspi-0.0.18.dist-info/METADATA
pylabdevs_tspspi-0.0.18.dist-info/WHEEL
pylabdevs_tspspi-0.0.18.dist-info/top_level.txt
pylabdevs_tspspi-0.0.18.dist-info/RECORD
