Metadata-Version: 2.1
Name: pylabdevs-tspspi
Version: 0.0.18
Summary: Lab devices base classes
Home-page: https://github.com/tspspi/pylabdevs
Author: Thomas Spielauer
Author-email: pypipackages01@tspi.at
Classifier: Programming Language :: Python :: 3
Classifier: License :: OSI Approved :: BSD License
Classifier: Operating System :: OS Independent
Requires-Python: >=3.6
License-File: LICENSE.md
Requires-Dist: numpy>=1.22.4
